setup.py
shine/__init__.py
shine.egg-info/PKG-INFO
shine.egg-info/SOURCES.txt
shine.egg-info/dependency_links.txt
shine.egg-info/not-zip-safe
shine.egg-info/requires.txt
shine.egg-info/top_level.txt
shine/bin/shine
shine/contrib/__init__.py
shine/contrib/virtual_request.py
shine/forwarder/__init__.py
shine/forwarder/forwarder.py
shine/gateway/__init__.py
shine/gateway/gateway.py
shine/gateway/server/__init__.py
shine/gateway/server/connection.py
shine/gateway/server/mixins.py
shine/gateway/server/server.py
shine/gateway/server/timer.py
shine/share/__init__.py
shine/share/cleaner.py
shine/share/config.py
shine/share/constants.py
shine/share/log.py
shine/share/proc_mgr.py
shine/share/share_store.py
shine/share/shine_pb2.py
shine/share/task.py
shine/share/utils.py
shine/trigger/__init__.py
shine/trigger/trigger.py
shine/worker/__init__.py
shine/worker/blueprint.py
shine/worker/connection.py
shine/worker/mixins.py
shine/worker/request.py
shine/worker/worker.py