Metadata-Version: 1.0
Name: shine
Version: 0.2.11
Summary: shine
Home-page: https://github.com/dantezhu/shine
Author: dantezhu
Author-email: zny2008@gmail.com
License: MIT
Platform: any
